{"cameraMode":{"drawMode":0,"name":"Shaded","section":"Shading Mode"},"sceneLighting":false,"audioPlay":false,"sceneViewState":{"m_AlwaysRefresh":false,"showFog":true,"showSkybox":false,"showFlares":true,"showImageEffects":true,"showParticleSystems":true,"showVisualEffectGraphs":true,"m_FxEnabled":true},"in2DMode":false,"pivot":{"x":-37.990684509277347,"y":4.992474555969238,"z":2.540391445159912},"rotation":{"x":-0.3058542013168335,"y":0.09226536750793457,"z":-0.029948493465781213,"w":-0.947333812713623},"size":5.7485880851745609,"orthographic":false}